fraud_detection_module/fraud_detection.py
src/fraud_detection.py
fraud_detection_module-0.0.5.dist-info/METADATA
fraud_detection_module-0.0.5.dist-info/WHEEL
fraud_detection_module-0.0.5.dist-info/license_files/LICENSE
fraud_detection_module-0.0.5.dist-info/RECORD
