Metadata-Version: 2.1
Name: fraud-detection-module
Version: 0.0.5
Summary: A fraud detection package for specific use case.
Author-email: Pranav Chaturvedi <pranavchat14@gmail.com>
License: Copyright (c) 2018 The Python Packaging Authority
Classifier: License :: OSI Approved :: MIT License
Classifier: Operating System :: OS Independent
Classifier: Programming Language :: Python :: 3
Requires-Python: >=3.7
